README.rst
setup.py
localemeasurement/__init__.py
localemeasurement/localeconversion.py
localemeasurement.egg-info/PKG-INFO
localemeasurement.egg-info/SOURCES.txt
localemeasurement.egg-info/dependency_links.txt
localemeasurement.egg-info/not-zip-safe
localemeasurement.egg-info/requires.txt
localemeasurement.egg-info/top_level.txt