Metadata-Version: 1.1
Name: localemeasurement
Version: 0.0.5
Summary: locale based measurement
Home-page: https://github.com/srcecde/locale-measurement
Author: Srce Cde (Chirag Rathod)
Author-email: chiragr83@gmail.com
License: MIT
Keywords: locale,measurement,unit,conversion
Platform: UNKNOWN
Classifier: Development Status :: 3 - Alpha
Classifier: License :: OSI Approved :: MIT License
Classifier: Programming Language :: Python :: 3
